st_rating/__init__.py
st_rating/frontend/build/asset-manifest.json
st_rating/frontend/build/bootstrap.min.css
st_rating/frontend/build/index.html
st_rating/frontend/build/static/js/main.b0be312f.js
st_rating/frontend/build/static/js/main.b0be312f.js.LICENSE.txt
st_rating/frontend/build/static/js/main.b0be312f.js.map
st_rating-0.0.2.dist-info/LICENSE
st_rating-0.0.2.dist-info/METADATA
st_rating-0.0.2.dist-info/WHEEL
st_rating-0.0.2.dist-info/top_level.txt
st_rating-0.0.2.dist-info/RECORD
